foxglove2zmq/__init__.py
foxglove2zmq/cli.py
foxglove2zmq/relay.py
foxglove2zmq-0.1.2.1.dist-info/licenses/LICENSE.md
foxglove2zmq-0.1.2.1.dist-info/METADATA
foxglove2zmq-0.1.2.1.dist-info/WHEEL
foxglove2zmq-0.1.2.1.dist-info/entry_points.txt
foxglove2zmq-0.1.2.1.dist-info/top_level.txt
foxglove2zmq-0.1.2.1.dist-info/RECORD
