Metadata-Version: 2.4
Name: foxglove2zmq
Version: 0.1.2.1
Summary: A relay for forwarding Foxglove WebSocket messages to a ZMQ server.
Author-email: Hamza El-Kebir <ha.elkebir@gmail.com>
Project-URL: Homepage, https://github.com/helkebir/foxglove2zmq
Project-URL: Bug Tracker, https://github.com/helkebir/foxglove2zmq/issues
Classifier: Programming Language :: Python :: 3
Classifier: License :: OSI Approved :: MIT License
Classifier: Operating System :: OS Independent
Classifier: Topic :: System :: Networking
Classifier: Framework :: AsyncIO
Requires-Python: >=3.7
License-File: LICENSE.md
Requires-Dist: websockets>=10.0
Requires-Dist: pyzmq>=22.0
Requires-Dist: protobuf>=3.19
Dynamic: license-file
